tests/__init__.py
tests/conftest.py
tests/test_backends.py
tests/test_cachable.py
tests/test_core.py
tests/test_env.py
tests/test_json_encoder.py
tests/test_metrics.py
tests/test_model_selection.py
tests/test_optimizer.py
tests/test_run.py
tests/test_sklearn_extend.py
tests/test_utils.py
tests/test_visualize.py
tests/utils.py
tests/backend_tests/__init__.py
tests/backend_tests/test_experiment.py
tests/estimators_test/__init__.py
tests/estimators_test/conftest.py
tests/estimators_test/test_base.py
tests/estimators_test/test_boosting.py
tests/estimators_test/test_ensemble.py
tests/estimators_test/test_linear.py
tests/estimators_test/test_neural_netrowk.py
tests/estimators_test/test_svm.py
tests/featureset_tests/__init__.py
tests/featureset_tests/test_base.py
tests/featureset_tests/test_decomposition.py
vivid/__init__.py
vivid/cacheable.py
vivid/core.py
vivid/env.py
vivid/json_encoder.py
vivid/metrics.py
vivid/model_selection.py
vivid/optimizers.py
vivid/runner.py
vivid/setup.py
vivid/text.py
vivid/utils.py
vivid/version.py
vivid/visualize.py
vivid/backends/__init__.py
vivid/backends/dataframes.py
vivid/backends/experiments.py
vivid/estimators/__init__.py
vivid/estimators/base.py
vivid/estimators/ensumble.py
vivid/estimators/evaluations.py
vivid/estimators/kneighbor.py
vivid/estimators/linear.py
vivid/estimators/neural_network.py
vivid/estimators/ngboost.py
vivid/estimators/svm.py
vivid/estimators/utils.py
vivid/estimators/boosting/__init__.py
vivid/estimators/boosting/block.py
vivid/estimators/boosting/catboost.py
vivid/estimators/boosting/helpers.py
vivid/estimators/boosting/lgbm.py
vivid/estimators/boosting/mixins.py
vivid/estimators/boosting/xgboost.py
vivid/features/__init__.py
vivid/features/base.py
vivid/features/datablock.py
vivid/features/decomposition.py
vivid/features/engine.py
vivid/sklearn_extend/__init__.py
vivid/sklearn_extend/neural_network.py
vivid/sklearn_extend/wrapper.py
python_vivid-0.3.3.5.dist-info/LICENSE
python_vivid-0.3.3.5.dist-info/METADATA
python_vivid-0.3.3.5.dist-info/WHEEL
python_vivid-0.3.3.5.dist-info/top_level.txt
python_vivid-0.3.3.5.dist-info/RECORD
