Metadata-Version: 2.1
Name: python-vivid
Version: 0.3.3.5
Summary: Support Tools for Machine Learning VIVIDLY
Home-page: https://atma.co.jp/
Author: nyk510
Author-email: yamaguchi@atma.co.jp
License: BSD License
Platform: UNKNOWN
Classifier: Framework :: Matplotlib
Classifier: Framework :: Pytest
Classifier: Intended Audience :: Developers
Classifier: License :: OSI Approved :: BSD License
Classifier: Operating System :: OS Independent
Classifier: Programming Language :: JavaScript
Classifier: Programming Language :: Python
Classifier: Programming Language :: Python :: 3.6
Classifier: Programming Language :: Python :: 3.7
Classifier: Programming Language :: Python :: 3.8
Requires-Dist: tqdm
Requires-Dist: numpy
Requires-Dist: matplotlib
Requires-Dist: seaborn
Requires-Dist: scikit-learn
Requires-Dist: scipy
Requires-Dist: pandas
Requires-Dist: joblib
Requires-Dist: optuna
Requires-Dist: xgboost
Requires-Dist: lightgbm
Requires-Dist: feather-format
Requires-Dist: tabulate
Requires-Dist: networkx
Provides-Extra: document
Requires-Dist: sphinx ; extra == 'document'
Requires-Dist: sphinx-rtd-theme ; extra == 'document'
Provides-Extra: test
Requires-Dist: pytest ; extra == 'test'
Requires-Dist: pytest-cov ; extra == 'test'
Requires-Dist: parameterized ; extra == 'test'
Requires-Dist: ipython ; extra == 'test'
Requires-Dist: jupyter ; extra == 'test'
Requires-Dist: notebook ; extra == 'test'
Requires-Dist: tornado (==5.1.1) ; extra == 'test'
Requires-Dist: keras (<=2.3.1) ; extra == 'test'
Requires-Dist: tensorflow (<=2.2.1) ; extra == 'test'
Requires-Dist: comet-ml ; extra == 'test'
